invoketool/__init__.py
invoketool-0.0.0.dist-info/METADATA
invoketool-0.0.0.dist-info/WHEEL
invoketool-0.0.0.dist-info/top_level.txt
invoketool-0.0.0.dist-info/RECORD
